AUTHORS.rst
HISTORY.rst
MANIFEST.in
README.rst
setup.cfg
setup.py
python_TAMER.egg-info/PKG-INFO
python_TAMER.egg-info/SOURCES.txt
python_TAMER.egg-info/dependency_links.txt
python_TAMER.egg-info/not-zip-safe
python_TAMER.egg-info/requires.txt
python_TAMER.egg-info/top_level.txt
python_tamer/ExposureMap.py
python_tamer/SpecificDoses.py
python_tamer/__init__.py
python_tamer/subroutines.py
python_tamer/config/python_tamer.conf
test/UV_test_data_2018.nc
test/test_dummy_library.py