Metadata-Version: 2.1
Name: python-TAMER
Version: 0.3.1
Summary: Toolkit for Analysis and Maps of Exposure Risk
Home-page: https://github.com/tch521/python-TAMER
Author: Todd C. Harris
Author-email: todd.harris@meteoswiss.ch
License: BSD-3-Clause license
Keywords: python-TAMER UV
Platform: UNKNOWN
Classifier: Development Status :: 3 - Alpha
Classifier: Intended Audience :: Developers
Classifier: Intended Audience :: Science/Research
Classifier: License :: OSI Approved :: BSD License
Classifier: Natural Language :: English
Classifier: Programming Language :: Python :: 3
Provides-Extra: test
